{
  "menu": [
    {
      "url": "/",
      "icon": "menu-icon tf-icons ti ti-dashboard",
      "name": "Dashboard",
      "slug": "dashboard"
    },
    {
      "url": "admin/order",
      "icon": "menu-icon ti ti-loader ti-spin",
      "name": "ORDERS",
      "slug": "order"
    },
    {
      "url": "admin/inventory",
      "icon": "menu-icon ti ti-folder",
      "name": "Inventory",
      "slug": "inventory"
    },
    {
      "url": "admin/inbound",
      "icon": "menu-icon ti ti-arrow-big-right ti-fade-right",
      "name": "Inbound",
      "slug": "inbound"
    },
    {
      "url": "admin/outbound",
      "icon": "menu-icon tf-icons ti ti-arrow-big-left ti-fade-left",
      "name": "Outbound",
      "slug": "outbound"
    },
    {
      "url": "admin/invoice",
      "icon": "menu-icon tf-icons ti ti-receipt",
      "name": "Invoice",
      "slug": "invoice"
    },
    {
      "url": "admin/report",
      "icon": "menu-icon ti ti-report-analytics",
      "name": "Reports",
      "slug": "report"
    }
  ]
}